{"id":"src\\shared\\random-number5.tsx","dependencies":[{"name":"D:\\desktop\\gg\\WgGRGvfAVyp5\\tsconfig.json","includedInParent":true,"mtime":1649340812201},{"name":"D:\\desktop\\gg\\WgGRGvfAVyp5\\package.json","includedInParent":true,"mtime":1649232423325}],"generated":{"js":"\"use strict\";\n\nObject.defineProperty(exports, \"__esModule\", { value: true });\nexports.arr = void 0;\nsetInterval(function () {\n    arr = new Array(5).fill(0);\n    for (var i = 0; i < 100; i++) {\n        var num = Math.trunc(Math.random() * 10);\n        arr[~~(num / 2)]++;\n    }\n    return arr;\n});","map":{"mappings":[{"source":"src\\shared\\random-number5.tsx","name":null,"original":{"line":1,"column":0},"generated":{"line":5,"column":0}},{"source":"src\\shared\\random-number5.tsx","name":null,"original":{"line":1,"column":12},"generated":{"line":5,"column":12}},{"source":"src\\shared\\random-number5.tsx","name":null,"original":{"line":1,"column":12},"generated":{"line":5,"column":24}},{"source":"src\\shared\\random-number5.tsx","name":null,"original":{"line":2,"column":2},"generated":{"line":6,"column":0}},{"source":"src\\shared\\random-number5.tsx","name":null,"original":{"line":2,"column":8},"generated":{"line":6,"column":10}},{"source":"src\\shared\\random-number5.tsx","name":null,"original":{"line":2,"column":12},"generated":{"line":6,"column":14}},{"source":"src\\shared\\random-number5.tsx","name":null,"original":{"line":2,"column":8},"generated":{"line":6,"column":19}},{"source":"src\\shared\\random-number5.tsx","name":null,"original":{"line":2,"column":18},"generated":{"line":6,"column":20}},{"source":"src\\shared\\random-number5.tsx","name":null,"original":{"line":2,"column":8},"generated":{"line":6,"column":21}},{"source":"src\\shared\\random-number5.tsx","name":null,"original":{"line":2,"column":21},"generated":{"line":6,"column":23}},{"source":"src\\shared\\random-number5.tsx","name":null,"original":{"line":2,"column":8},"generated":{"line":6,"column":27}},{"source":"src\\shared\\random-number5.tsx","name":null,"original":{"line":2,"column":26},"generated":{"line":6,"column":28}},{"source":"src\\shared\\random-number5.tsx","name":null,"original":{"line":2,"column":8},"generated":{"line":6,"column":29}},{"source":"src\\shared\\random-number5.tsx","name":null,"original":{"line":2,"column":2},"generated":{"line":6,"column":30}},{"source":"src\\shared\\random-number5.tsx","name":null,"original":{"line":3,"column":2},"generated":{"line":7,"column":0}},{"source":"src\\shared\\random-number5.tsx","name":null,"original":{"line":3,"column":7},"generated":{"line":7,"column":9}},{"source":"src\\shared\\random-number5.tsx","name":null,"original":{"line":3,"column":11},"generated":{"line":7,"column":13}},{"source":"src\\shared\\random-number5.tsx","name":null,"original":{"line":3,"column":15},"generated":{"line":7,"column":17}},{"source":"src\\shared\\random-number5.tsx","name":null,"original":{"line":3,"column":2},"generated":{"line":7,"column":18}},{"source":"src\\shared\\random-number5.tsx","name":null,"original":{"line":3,"column":18},"generated":{"line":7,"column":20}},{"source":"src\\shared\\random-number5.tsx","name":null,"original":{"line":3,"column":22},"generated":{"line":7,"column":24}},{"source":"src\\shared\\random-number5.tsx","name":null,"original":{"line":3,"column":2},"generated":{"line":7,"column":27}},{"source":"src\\shared\\random-number5.tsx","name":null,"original":{"line":3,"column":27},"generated":{"line":7,"column":29}},{"source":"src\\shared\\random-number5.tsx","name":null,"original":{"line":3,"column":2},"generated":{"line":7,"column":32}},{"source":"src\\shared\\random-number5.tsx","name":null,"original":{"line":3,"column":32},"generated":{"line":7,"column":34}},{"source":"src\\shared\\random-number5.tsx","name":null,"original":{"line":4,"column":4},"generated":{"line":8,"column":0}},{"source":"src\\shared\\random-number5.tsx","name":null,"original":{"line":4,"column":8},"generated":{"line":8,"column":12}},{"source":"src\\shared\\random-number5.tsx","name":null,"original":{"line":4,"column":14},"generated":{"line":8,"column":18}},{"source":"src\\shared\\random-number5.tsx","name":null,"original":{"line":4,"column":19},"generated":{"line":8,"column":23}},{"source":"src\\shared\\random-number5.tsx","name":null,"original":{"line":4,"column":14},"generated":{"line":8,"column":28}},{"source":"src\\shared\\random-number5.tsx","name":null,"original":{"line":4,"column":25},"generated":{"line":8,"column":29}},{"source":"src\\shared\\random-number5.tsx","name":null,"original":{"line":4,"column":30},"generated":{"line":8,"column":34}},{"source":"src\\shared\\random-number5.tsx","name":null,"original":{"line":4,"column":25},"generated":{"line":8,"column":40}},{"source":"src\\shared\\random-number5.tsx","name":null,"original":{"line":4,"column":41},"generated":{"line":8,"column":45}},{"source":"src\\shared\\random-number5.tsx","name":null,"original":{"line":4,"column":14},"generated":{"line":8,"column":47}},{"source":"src\\shared\\random-number5.tsx","name":null,"original":{"line":4,"column":4},"generated":{"line":8,"column":48}},{"source":"src\\shared\\random-number5.tsx","name":null,"original":{"line":5,"column":4},"generated":{"line":9,"column":0}},{"source":"src\\shared\\random-number5.tsx","name":null,"original":{"line":5,"column":8},"generated":{"line":9,"column":12}},{"source":"src\\shared\\random-number5.tsx","name":null,"original":{"line":5,"column":9},"generated":{"line":9,"column":13}},{"source":"src\\shared\\random-number5.tsx","name":null,"original":{"line":5,"column":11},"generated":{"line":9,"column":15}},{"source":"src\\shared\\random-number5.tsx","name":null,"original":{"line":5,"column":17},"generated":{"line":9,"column":21}},{"source":"src\\shared\\random-number5.tsx","name":null,"original":{"line":5,"column":9},"generated":{"line":9,"column":22}},{"source":"src\\shared\\random-number5.tsx","name":null,"original":{"line":5,"column":4},"generated":{"line":9,"column":23}},{"source":"src\\shared\\random-number5.tsx","name":null,"original":{"line":6,"column":3},"generated":{"line":10,"column":0}},{"source":"src\\shared\\random-number5.tsx","name":null,"original":{"line":7,"column":2},"generated":{"line":11,"column":0}},{"source":"src\\shared\\random-number5.tsx","name":null,"original":{"line":7,"column":9},"generated":{"line":11,"column":11}},{"source":"src\\shared\\random-number5.tsx","name":null,"original":{"line":7,"column":2},"generated":{"line":11,"column":14}},{"source":"src\\shared\\random-number5.tsx","name":null,"original":{"line":8,"column":1},"generated":{"line":12,"column":0}},{"source":"src\\shared\\random-number5.tsx","name":null,"original":{"line":1,"column":0},"generated":{"line":12,"column":1}}],"sources":{"src\\shared\\random-number5.tsx":"setInterval(() => {\r\n  arr = new Array(5).fill(0)\r\n  for (let i = 0; i < 100; i++) {\r\n    let num = Math.trunc(Math.random() * 10)\r\n    arr[~~(num / 2)]++\r\n  }\r\n  return arr\r\n})\r\nexport { arr }\r\n"},"lineCount":null}},"hash":"c14fe0a8b9c37e3d13b3d91c0bfdf65e","cacheData":{"env":{}}}